friktionless/__init__.py
friktionless/zaps.py
friktionless-0.0.4.dist-info/WHEEL
friktionless-0.0.4.dist-info/METADATA
friktionless-0.0.4.dist-info/RECORD
