Metadata-Version: 2.1
Name: friktionless
Version: 0.0.4
Summary: Friktionless is a Python package providing simplified interfaces to Friktion data. It aims to be the fundamental building block for doing data engineering and data analysis in Python for Friktion.
Home-page: https://github.com/Friktion-Labs/friktionless
License: Proprietary
Keywords: friktion,solana,dov,finance
Author: Friktion core team
Author-email: team@friktionlabs.com
Requires-Python: >=3.7,<3.10
Classifier: License :: Other/Proprietary License
Classifier: Programming Language :: Python :: 3
Classifier: Programming Language :: Python :: 3.7
Classifier: Programming Language :: Python :: 3.8
Classifier: Programming Language :: Python :: 3.9
Requires-Dist: altair (>=4.2.0,<5.0.0)
Requires-Dist: altair-saver (>=0.5.0,<0.6.0)
Requires-Dist: ccxt (==1.83.58)
Requires-Dist: google-cloud-storage (>=2.3.0,<3.0.0)
Requires-Dist: pandas (==1.3.5)
Requires-Dist: pandas-gbq (>=0.17.5,<0.18.0)
Requires-Dist: selenium (>=4.1.5,<5.0.0)
Project-URL: Bug Tracker, https://github.com/Friktion-Labs/friktionless/issues
Project-URL: Repository, https://github.com/Friktion-Labs/friktionless
